[
    {
        "id": "8143acbd-38f9-46f3-86b5-9b2e2a463d21",
        "name": "Марко",
        "surname": "Дојкић",
        "email": "marko.dojkic.18@singimail.rs",
        "password": "C8DOYxsi1aOdHqHEK8L+dA==",
        "favorites": [
            "Рачунарска опрема",
            "Рачунари"
        ],
        "phone": "",
        "mobilePhone": "0654655562",
        "planer": [
            {
                "date": "2021-05-26T10:16:06.912Z",
                "tour": "85e94363-8c01-42a2-bae8-649f49328d6e"
            },
            {
                "date": "2021-04-11T04:05:42.685Z",
                "tour": "e4727b5a-3b25-4cf1-a3a7-546a6b33039a"
            },
            {
                "date": "2021-09-22T00:52:46.076Z",
                "tour": "4a4ce8c5-4452-4900-b585-dc305f8298c4"
            },
            {
                "date": "2021-05-27T20:18:06.182Z",
                "tour": "9337a7cb-d639-4964-9982-d4b6e284d64a"
            },
            {
                "date": "2021-06-02T18:56:31.775Z",
                "tour": "004315e5-cdf8-4494-a2dc-07e699f55415"
            },
            {
                "date": "2021-10-02T02:58:53.499Z",
                "tour": "3a76c841-8aaf-4da2-859b-7f1744611b9e"
            },
            {
                "date": "2021-11-04T00:37:42.871Z",
                "tour": "25960a68-e154-4b80-9e89-35f1e3875582"
            },
            {
                "date": "2021-03-31T01:55:11.623Z",
                "tour": "82303a52-f55b-4916-9908-38d478b86d24"
            },
            {
                "date": "2021-09-27T18:35:15.831Z",
                "tour": "eccd1db5-73a6-4afd-a88c-17b40b4fbe07"
            },
            {
                "date": "2021-09-30T10:36:37.748Z",
                "tour": "297dccf8-18fb-4f54-8c14-7a30383a7cba"
            },
            {
                "date": "2021-02-12T01:36:32.974Z",
                "tour": "956fe5ae-0c1e-48a7-977b-3a173ae60845"
            },
            {
                "date": "2021-03-23T10:06:33.612Z",
                "tour": "68f4b3bc-4904-4ab2-bb42-15cba43c001b"
            },
            {
                "date": "2021-07-01T23:08:54.011Z",
                "tour": "264f24ac-f0a0-45a9-b1d8-47cd732ea219"
            },
            {
                "date": "2021-08-06T23:33:47.986Z",
                "tour": "052d8d3e-5f00-4c86-b483-4a68913c9537"
            }
        ]
    },
    {
        "id": "fd40451e-220f-46d4-bd2e-3c8a1a359431",
        "name": "Joe",
        "surname": "Ellery",
        "email": "lethimgo21@joe.svu",
        "password": "YJNXRCRBTnDtdNSZd9zOu0Ks7yhn2PiiuLCMWB+jg4Q=",
        "favorites": [
            "Музички уређаји",
            "Савремена техника"
        ],
        "phone": "0124789632",
        "mobilePhone": "0651204564",
        "planer": [
            {
                "date": "2021-09-17T16:15:57.881Z",
                "tour": "faf9e8b1-3fd2-475b-9e8e-ee604d7e9cbb"
            },
            {
                "date": "2021-10-24T07:54:33.200Z",
                "tour": "b0c4ab7a-eb3b-43c3-a70b-64b03d167afc"
            },
            {
                "date": "2021-07-08T23:39:10.942Z",
                "tour": "4cb1aa47-bccd-4ae5-a210-e7818eff3127"
            },
            {
                "date": "2021-10-30T10:44:04.453Z",
                "tour": "58e46fe4-a757-48f6-b461-e3f310b5aa3a"
            },
            {
                "date": "2021-10-25T04:08:22.231Z",
                "tour": "e6016e27-a05f-4cb7-814f-0e56e156a527"
            },
            {
                "date": "2021-05-04T22:00:30.040Z",
                "tour": "51b35705-d8a6-4d12-b9c5-4a16750596db"
            },
            {
                "date": "2021-06-26T09:00:16.155Z",
                "tour": "e7ef0868-780a-4239-8d6f-66a0413c3603"
            },
            {
                "date": "2021-05-08T13:47:13.730Z",
                "tour": "b58b4d34-e8fc-4d03-8bb0-910374f062e7"
            }
        ]
    },
    {
        "id": "9b87af16-c100-41b2-8685-e3a9514195a1",
        "name": "Earline",
        "surname": "Bullock",
        "email": "earlinebullock@kyagoro.com",
        "favorites": [
            "Рачунари",
            "Савремена техника",
            "Техника 70-их"
        ],
        "phone": 9654153217,
        "mobilePhone": 8915263733,
        "planer": [
            {
                "date": "2021-07-29T16:45:44.529Z",
                "tour": "2722512e-e1e4-4719-9391-5ba768f0e2c8"
            },
            {
                "date": "2021-12-11T03:53:47.956Z",
                "tour": "6e26d0fc-0eae-4822-a3d7-8c7aeac511c1"
            },
            {
                "date": "2022-01-04T05:37:45.773Z",
                "tour": "b36868e4-0199-47af-89a5-4b6ed8692a26"
            },
            {
                "date": "2022-01-28T18:20:40.572Z",
                "tour": "f359a941-3d5a-48ac-bfa9-46fe92b8978a"
            },
            {
                "date": "2021-04-14T15:19:01.160Z",
                "tour": "c4a56166-ae44-40fd-b230-e2029716332f"
            },
            {
                "date": "2021-06-26T08:15:21.090Z",
                "tour": "8cf53f75-7762-4508-87ef-5959622026ce"
            },
            {
                "date": "2022-01-02T21:13:59.537Z",
                "tour": "49a9f066-e460-43e9-a78f-19766f27be05"
            },
            {
                "date": "2021-04-26T10:40:32.739Z",
                "tour": "eb3a8724-8e91-4c43-bc69-8947a4e45904"
            },
            {
                "date": "2021-03-30T05:49:07.508Z",
                "tour": "a44a992f-a8f8-43e7-8c3d-2c4c00c523c6"
            },
            {
                "date": "2021-02-28T16:58:55.188Z",
                "tour": "c92b0c87-1630-4dce-940a-113d3c15af38"
            }
        ],
        "password": "ho+9YFJ8g+O+dKmxmPCOB+pdV7g4QGAC1bdb5Fz75rE="
    },
    {
        "id": "cf088d63-0977-41f8-b176-922b3f72fe5b",
        "name": "Morse",
        "surname": "Vang",
        "email": "morsevang@kyagoro.com",
        "favorites": [
            "Техника 80-их",
            "Телевизори",
            "Техника за забаву"
        ],
        "phone": 9585253377,
        "mobilePhone": 8404562867,
        "planer": [
            {
                "date": "2021-10-22T13:14:40.625Z",
                "tour": "2fc5b640-b3fa-423d-86ae-596b147caa60"
            },
            {
                "date": "2021-02-24T09:31:46.500Z",
                "tour": "9eb9b4a7-87b2-4d32-959a-2f8da4de6ee9"
            },
            {
                "date": "2021-10-28T13:42:15.353Z",
                "tour": "ab5c8f40-8dfe-44ed-b6fc-85213e014793"
            },
            {
                "date": "2021-02-27T22:59:42.721Z",
                "tour": "45df4a19-c524-4035-836e-988b52157607"
            },
            {
                "date": "2021-08-28T10:00:47.882Z",
                "tour": "558b5727-f3cf-431b-82c8-8fd7872a217d"
            },
            {
                "date": "2021-09-16T06:36:27.633Z",
                "tour": "511e6922-2d06-4534-b5a7-af58d384211c"
            },
            {
                "date": "2021-06-10T16:14:52.522Z",
                "tour": "d413c2d9-6c1e-40d6-8df1-0a8bf54177fc"
            },
            {
                "date": "2021-11-29T09:56:22.426Z",
                "tour": "de582f01-751f-4556-be08-286c1974569e"
            }
        ],
        "password": "lZV2Baj5haAnYwp0Tf8NBA=="
    },
    {
        "id": "6a379837-8c82-4d56-b116-f16cc69b8783",
        "name": "Castro",
        "surname": "Byers",
        "email": "castrobyers@kyagoro.com",
        "favorites": [
            "Савремена техника"
        ],
        "phone": 9504603801,
        "mobilePhone": 8324453947,
        "planer": [
            {
                "date": "2021-03-16T17:45:25.796Z",
                "tour": "fd98e930-accd-40ab-a9fa-a80d1c64966f"
            },
            {
                "date": "2021-02-15T06:54:21.483Z",
                "tour": "aa29bccb-916b-42bd-94a7-4084669fb423"
            },
            {
                "date": "2021-12-31T15:20:57.253Z",
                "tour": "02cb877f-53d7-4c52-9c40-505b0945c04b"
            },
            {
                "date": "2021-04-12T13:45:57.255Z",
                "tour": "ae1df614-5095-467e-85e6-559239b0826e"
            },
            {
                "date": "2022-01-23T01:12:55.466Z",
                "tour": "938e7910-62af-4a65-afb6-244aeb569677"
            },
            {
                "date": "2021-11-13T06:50:58.262Z",
                "tour": "f0d8d39b-e3f8-433d-96fd-652656d9b737"
            },
            {
                "date": "2021-06-16T04:01:56.596Z",
                "tour": "8f6705e1-feb5-4fe3-8c8b-7c43c2ea60ce"
            }
        ],
        "password": "5gI9ececGoRTkcWrseAt0rojh/6bFyqXdf1LhaYcdOw="
    },
    {
        "id": "40a5ca1a-b3c2-414d-b19d-8d43828e6478",
        "name": "Stone",
        "surname": "Sexton",
        "email": "stonesexton@kyagoro.com",
        "favorites": [
            "Телефони"
        ],
        "phone": 8135713269,
        "mobilePhone": 9474603176,
        "planer": [
            {
                "date": "2021-11-08T20:47:12.605Z",
                "tour": "c94de505-206c-4c6a-8169-e08bf5db609d"
            },
            {
                "date": "2021-05-22T12:55:10.799Z",
                "tour": "6fa403e8-bdbc-4d1c-876c-caefc16dc7e9"
            },
            {
                "date": "2021-11-05T09:26:13.526Z",
                "tour": "80677f32-1c4d-4488-8786-b3300221efd6"
            },
            {
                "date": "2021-07-13T23:18:36.701Z",
                "tour": "8f2e7093-2458-4633-8e83-d46cea4a2e7b"
            },
            {
                "date": "2021-10-30T18:42:57.379Z",
                "tour": "9c8d1981-285c-49b8-9931-0d74f32592eb"
            },
            {
                "date": "2021-12-22T19:13:14.269Z",
                "tour": "1cb495c6-c6b5-4c18-8bb9-520799285996"
            },
            {
                "date": "2022-01-27T10:51:18.377Z",
                "tour": "c0b6d5ff-ee5d-430f-8976-f0f68d25b83e"
            },
            {
                "date": "2021-11-01T07:07:59.616Z",
                "tour": "d71a571d-22a0-4349-a50d-b1b1a693431f"
            },
            {
                "date": "2021-04-15T09:24:18.479Z",
                "tour": "941a5c59-3bda-44a8-9709-700bd8b9e1f9"
            },
            {
                "date": "2021-02-08T03:32:48.212Z",
                "tour": "595879f9-16ba-4e6f-a254-334e6d47ed9d"
            }
        ],
        "password": "OLCH3tgrn6nPp0ENTM0nYA=="
    },
    {
        "id": "99c7c0ba-7e3d-4f7a-b0da-70c9bbfafe0f",
        "name": "Kane",
        "surname": "Brooks",
        "email": "kanebrooks@kyagoro.com",
        "favorites": [
            "Рачунарска опрема",
            "Техника 80-их",
            "Телевизори"
        ],
        "phone": 8305953573,
        "mobilePhone": 9515702310,
        "planer": [
            {
                "date": "2021-08-08T20:52:26.429Z",
                "tour": "25dee3e5-4f6c-4d35-b5a2-591750a3a5aa"
            },
            {
                "date": "2021-11-24T05:03:55.925Z",
                "tour": "11004252-ebea-43ff-8c95-96933d51e55d"
            },
            {
                "date": "2021-06-04T12:43:39.390Z",
                "tour": "0ada8595-68fc-4ca2-bd2d-d23a4a779af0"
            },
            {
                "date": "2021-02-21T14:14:09.182Z",
                "tour": "3f065d3d-0795-49cd-9c04-029d4f71b5be"
            },
            {
                "date": "2021-09-24T10:19:12.671Z",
                "tour": "066107e7-90fb-4cfa-b21b-ced44b88e6b2"
            },
            {
                "date": "2021-08-01T07:03:20.222Z",
                "tour": "64d90f1a-a8b4-466c-afcf-ab1f401f9dd1"
            },
            {
                "date": "2021-04-20T04:08:32.587Z",
                "tour": "863a502e-57a5-44b4-8448-9728264c872a"
            }
        ],
        "password": "pVbHhpXvmDFdx+TYx3RvxA=="
    },
    {
        "id": "cfac9840-ecc7-407f-b469-c0b2bef772eb",
        "name": "Castaneda",
        "surname": "Blackwell",
        "email": "castanedablackwell@kyagoro.com",
        "favorites": [
            "Техника 70-их",
            "Техника 90-их"
        ],
        "phone": 9925212737,
        "mobilePhone": 8314512268,
        "planer": [
            {
                "date": "2021-03-30T12:15:55.427Z",
                "tour": "0abf27e5-958e-4612-ae27-68f3a0cb260c"
            },
            {
                "date": "2021-07-23T19:14:12.082Z",
                "tour": "2aab2223-3e78-4455-b2c8-bee7b7f6e97b"
            },
            {
                "date": "2021-10-12T01:36:14.544Z",
                "tour": "bfba8ef9-d11e-43e3-8062-ca71c7302261"
            },
            {
                "date": "2021-08-17T21:26:41.073Z",
                "tour": "e87ddd4e-1eea-496c-a0cb-a23fc30add0e"
            },
            {
                "date": "2021-12-27T02:57:48.102Z",
                "tour": "be5cee6e-30ec-4bbd-b7b8-fc435e01c4b9"
            },
            {
                "date": "2021-10-04T12:52:21.697Z",
                "tour": "fde3fa24-fbc1-4265-8367-815fda237aea"
            },
            {
                "date": "2021-11-14T18:17:28.027Z",
                "tour": "366a7171-029c-409b-ab4c-6f2f7e34ced7"
            },
            {
                "date": "2021-09-25T23:54:22.666Z",
                "tour": "b81ff943-9556-41ef-81e4-2a223ac40ce6"
            },
            {
                "date": "2021-09-13T23:07:04.218Z",
                "tour": "7b13f321-005f-4bd2-a618-f1d3e7277f45"
            },
            {
                "date": "2021-03-24T07:07:40.324Z",
                "tour": "2b730ff5-5061-483e-b294-2631e31a45e8"
            },
            {
                "date": "2021-05-07T14:45:01.245Z",
                "tour": "3662a650-08ea-4deb-ba7c-07cf496451be"
            },
            {
                "date": "2021-09-14T11:06:59.221Z",
                "tour": "d729e81a-a0ba-462f-a7c5-350a36d990b4"
            }
        ],
        "password": "t8RAt4RraAK+AehV0uwDoPHPLTjIHYxaQo4WyNZAf08="
    },
    {
        "id": "6bd30c86-6d2a-4f0f-a9eb-b913ef44beb0",
        "name": "Rosalinda",
        "surname": "Rice",
        "email": "rosalindarice@kyagoro.com",
        "favorites": [
            "Телефони",
            "Техника 70-их",
            "Рачунари",
            "Техника 60-их"
        ],
        "phone": 9665733066,
        "mobilePhone": 8345752154,
        "planer": [
            {
                "date": "2021-07-09T20:23:00.004Z",
                "tour": "9f1d408b-7f9e-4975-a728-e78a1079417c"
            },
            {
                "date": "2021-04-26T12:56:35.413Z",
                "tour": "576f4891-6eed-40c9-b30d-2faa51137a25"
            },
            {
                "date": "2021-12-09T07:43:16.352Z",
                "tour": "a9ddc229-65db-45ce-86fc-0ddaa0465a8b"
            },
            {
                "date": "2022-01-10T23:01:42.951Z",
                "tour": "eb17f371-2309-4f7c-81aa-4df715b41d14"
            },
            {
                "date": "2021-09-24T09:43:34.541Z",
                "tour": "aa843db1-4334-4dc2-a24b-15ed1ad4b8fd"
            },
            {
                "date": "2021-01-09T10:09:54.656Z",
                "tour": "d499b68d-97bc-4135-b723-16844b31e1a8"
            },
            {
                "date": "2021-11-17T03:34:51.802Z",
                "tour": "0aab01a3-ba5d-412b-8eef-be538780b8db"
            },
            {
                "date": "2021-05-06T04:02:56.999Z",
                "tour": "a8d1f451-02c2-4942-9b97-cccfe28edde5"
            },
            {
                "date": "2021-04-08T17:14:11.321Z",
                "tour": "912ff6c0-879b-4fcb-b63a-62a1f3f21699"
            },
            {
                "date": "2021-09-27T14:42:13.034Z",
                "tour": "6e990461-c0c6-4c68-b9e8-264ffc266546"
            }
        ],
        "password": "B6gmoyBzzIrodSSVdn8o46qOTLANG7FbC79+C7L6FIU="
    },
    {
        "id": "f565a805-1320-4031-a739-cbdd578a8a4c",
        "name": "Brewer",
        "surname": "Atkins",
        "email": "breweratkins@kyagoro.com",
        "favorites": [
            "Техника 80-их",
            "Телефони",
            "Техника 90-их"
        ],
        "phone": 8304142908,
        "mobilePhone": 8105353519,
        "planer": [
            {
                "date": "2021-06-20T12:04:25.407Z",
                "tour": "87901b7d-8046-4e53-9d34-f6556eb4dc21"
            },
            {
                "date": "2021-07-04T14:34:24.061Z",
                "tour": "f8e7dce7-00fb-4182-be10-ac9c5deb36a0"
            },
            {
                "date": "2021-03-03T14:56:42.203Z",
                "tour": "266fcb67-e434-4ce6-bfe8-d3a32df48806"
            },
            {
                "date": "2021-09-03T02:27:12.691Z",
                "tour": "71bf79c4-18bf-43b9-a69a-8947af44a12f"
            },
            {
                "date": "2021-01-23T07:33:24.868Z",
                "tour": "e9383729-1a2b-47b3-a86e-f777d15f7b8b"
            },
            {
                "date": "2022-01-03T08:06:11.689Z",
                "tour": "b0a150ed-113f-4ea9-b4f3-a1a133775a09"
            },
            {
                "date": "2021-08-29T08:13:17.503Z",
                "tour": "808e46cd-c680-4553-acca-39ae28da37bf"
            },
            {
                "date": "2021-12-14T06:18:43.846Z",
                "tour": "2f568eb7-5b28-4069-9801-191ec6431835"
            },
            {
                "date": "2021-12-03T06:05:48.205Z",
                "tour": "f1c2d779-ff76-4162-90d3-dbb2dc0d5862"
            }
        ],
        "password": "GwsoHRPpWEy6yw7ca7F2hmZvzK9lTihgH+kjkFCX418="
    },
    {
        "id": "eb3e5d49-6de4-4b9e-b3e1-30daf52bd82a",
        "name": "Forbes",
        "surname": "Tran",
        "email": "forbestran@kyagoro.com",
        "favorites": [
            "Техника за забаву",
            "Савремена техника"
        ],
        "phone": 9065822542,
        "mobilePhone": 8534582980,
        "planer": [
            {
                "date": "2021-06-13T23:27:46.542Z",
                "tour": "dbb55d87-25b8-4407-a4b2-52bc11726469"
            },
            {
                "date": "2021-10-25T07:36:15.748Z",
                "tour": "460b5e97-2abd-4b9c-979d-fe1461a8b096"
            },
            {
                "date": "2021-12-16T04:08:02.073Z",
                "tour": "6ff74b92-a80f-43ab-91bf-019e633e0f71"
            },
            {
                "date": "2021-09-09T06:18:07.970Z",
                "tour": "9234efda-f00d-4b5a-8f02-ed1cfb7bb2c2"
            },
            {
                "date": "2021-10-13T03:43:06.922Z",
                "tour": "44e845a1-3686-42f4-ba6c-4ba11dbc1df3"
            },
            {
                "date": "2021-05-26T05:03:18.492Z",
                "tour": "540b344f-8691-4fb2-a2d0-e00476c0cd8d"
            },
            {
                "date": "2021-07-14T10:47:45.022Z",
                "tour": "48d6893d-f6be-49e9-84ad-716230ff5cc3"
            },
            {
                "date": "2021-04-16T15:08:50.910Z",
                "tour": "e6567f02-1fd9-4483-ba01-13aa45c183f5"
            },
            {
                "date": "2021-05-25T23:58:32.287Z",
                "tour": "61b8aefa-d6ce-4ae1-8feb-88199b597286"
            }
        ],
        "password": "zhzTJaeUagQXXAOR37CccoIHELOJ3G0/DN5TjwgVIdw="
    },
    {
        "id": "c275d38c-7315-46f0-a3ff-72b58aecce69",
        "name": "Mia",
        "surname": "Vargas",
        "email": "miavargas@kyagoro.com",
        "favorites": [
            "Техника 70-их",
            "Телевизори",
            "Рачунари"
        ],
        "phone": 9884102030,
        "mobilePhone": 9004542455,
        "planer": [
            {
                "date": "2021-01-12T09:24:05.967Z",
                "tour": "0ea5a189-26e0-4876-8ac3-c0b51348e5d3"
            },
            {
                "date": "2021-04-14T04:50:38.389Z",
                "tour": "611c7847-3aa5-42d4-94fa-d7381a0055ec"
            },
            {
                "date": "2021-07-12T09:10:49.741Z",
                "tour": "e0b5d302-a282-4d49-a5fc-f2dfeb8da5e7"
            },
            {
                "date": "2021-06-30T20:39:53.599Z",
                "tour": "6ecd728d-eae5-4bde-871a-54a77303dcac"
            },
            {
                "date": "2021-10-08T02:52:32.246Z",
                "tour": "5aadb0df-c356-4896-94cc-e30260e4114c"
            },
            {
                "date": "2021-08-31T14:47:09.132Z",
                "tour": "8bd763fd-17be-4d59-8adb-500ee8efcfc9"
            },
            {
                "date": "2021-02-06T23:30:57.140Z",
                "tour": "2b026748-051a-4796-9757-54fe44355cad"
            }
        ],
        "password": "ieePhi+x59VGyqgPqjF0NA=="
    },
    {
        "id": "14257c9d-3ade-4cf6-a0bc-555cdc02b372",
        "name": "Margret",
        "surname": "Burch",
        "email": "margretburch@kyagoro.com",
        "favorites": [
            "Техника 70-их",
            "Техника 80-их",
            "Техника 60-их"
        ],
        "phone": 9474823779,
        "mobilePhone": 8534262246,
        "planer": [
            {
                "date": "2021-10-29T07:03:39.614Z",
                "tour": "f4700e9b-afbe-4f14-9226-197f80ee441f"
            },
            {
                "date": "2021-06-14T04:52:39.930Z",
                "tour": "25f3cb7c-79b8-4dd2-b7f3-1be6082dc22a"
            },
            {
                "date": "2021-10-23T20:05:48.726Z",
                "tour": "7abd6421-6f88-45da-9cdb-e7d4d30fc82b"
            },
            {
                "date": "2022-01-13T16:30:34.801Z",
                "tour": "e24bc01f-37e4-495a-9039-7b08b3d4420e"
            },
            {
                "date": "2021-02-06T01:48:04.311Z",
                "tour": "7e418c04-b7ea-4d1f-a93c-9a65dafb3a88"
            },
            {
                "date": "2021-02-12T04:06:45.600Z",
                "tour": "35d2effe-7df1-4b41-bf3a-5734d4d1cc7e"
            },
            {
                "date": "2021-06-29T02:35:40.571Z",
                "tour": "a0a7566a-9ba4-4398-8fca-b5447eebb145"
            }
        ],
        "password": "BL8VGDyVzfOzq8uZ86BS9NGb+4IKNQ//vSxGWIMGANg="
    },
    {
        "id": "56ad2423-a727-4f06-83d8-ec784084eace",
        "name": "Janie",
        "surname": "Jones",
        "email": "janiejones@kyagoro.com",
        "favorites": [
            "Техника 60-их",
            "Рачунари",
            "Рачунарска опрема",
            "Техника 90-их"
        ],
        "phone": 9375643125,
        "mobilePhone": 8884942266,
        "planer": [
            {
                "date": "2021-04-21T12:18:38.312Z",
                "tour": "6f584c2a-1e7c-4b00-bd50-6683ea30a457"
            },
            {
                "date": "2021-10-06T09:05:32.148Z",
                "tour": "f2075a8f-799b-4e2c-a67b-ce47ec8dcb12"
            },
            {
                "date": "2021-04-24T08:56:31.714Z",
                "tour": "bdf592f1-d0c6-4c31-8202-ff2155138520"
            }
        ],
        "password": "Xwq/OGXAA2IglU15Anm/CA=="
    },
    {
        "id": "564ecaf7-41a7-4c89-b2e9-74c9217cc8f3",
        "name": "Francisca",
        "surname": "Rich",
        "email": "franciscarich@kyagoro.com",
        "favorites": [
            "Техника 70-их",
            "Рачунарска опрема",
            "Техника за забаву"
        ],
        "phone": 9774643506,
        "mobilePhone": 9224253895,
        "planer": [],
        "password": "UuKZUn6cJ4iW68S+l4O0UCHCm+Vgo6DiLB1OI7liF4c="
    },
    {
        "id": "8a82b824-1fce-4b7e-aae5-5a0d8cf1049d",
        "name": "Kay",
        "surname": "Gay",
        "email": "kaygay@kyagoro.com",
        "favorites": [
            "Техника 60-их",
            "Техника 70-их",
            "Техника 80-их"
        ],
        "phone": 8555383309,
        "mobilePhone": 9814512083,
        "planer": [],
        "password": "op5tm7d0mdI6H0op73+PDw=="
    },
    {
        "id": "5c6d6f55-f4d9-4980-89ba-7c28982976c5",
        "name": "Lourdes",
        "surname": "Hewitt",
        "email": "lourdeshewitt@kyagoro.com",
        "favorites": [
            "Савремена техника",
            "Рачунари"
        ],
        "phone": 9644593556,
        "mobilePhone": 8184292222,
        "planer": [],
        "password": "hfcHabogzGNMxBncgfhdddWh4Nn7cwFqU5qdGHF2GeI="
    }
]